aparatdl/__init__.py
aparatdl/exceptions.py
aparatdl/main.py
aparatdl/scraper.py
aparatdl-1.0.0.dist-info/LICENSE.txt
aparatdl-1.0.0.dist-info/METADATA
aparatdl-1.0.0.dist-info/WHEEL
aparatdl-1.0.0.dist-info/top_level.txt
aparatdl-1.0.0.dist-info/RECORD
